rootsense2/__init__.py
rootsense2/chart.py
rootsense2/osInfo.py
rootsense2/predict.py
rootsense2/rei.py
rootsense2/report.py
rootsense2/root.py
rootsense2/thrading.py
rootsense2/ticket.py
rootsense2.0-2.1.0.dist-info/LICENSE
rootsense2.0-2.1.0.dist-info/METADATA
rootsense2.0-2.1.0.dist-info/WHEEL
rootsense2.0-2.1.0.dist-info/entry_points.txt
rootsense2.0-2.1.0.dist-info/top_level.txt
rootsense2.0-2.1.0.dist-info/RECORD
