Metadata-Version: 2.1
Name: rootsense2.0
Version: 2.1.0
Summary: A multithreading application for system monitoring and resource analysis.
Author: Amey Yarnalkar
Author-email: yarnalkaramey@gmail.com
License: MIT
Classifier: Programming Language :: Python :: 3
Classifier: License :: OSI Approved :: MIT License
Classifier: Operating System :: OS Independent
Requires-Python: >=3.6
License-File: LICENSE
Requires-Dist: pymongo
Requires-Dist: streamlit
Requires-Dist: scipy
Requires-Dist: sklearn
Requires-Dist: pandas
Requires-Dist: numpy
Requires-Dist: psutil
Requires-Dist: time
Requires-Dist: datetime
Requires-Dist: logging
Requires-Dist: argparse
Requires-Dist: plotly
Requires-Dist: os
